[{"description":"","id":"counter","keyword":"Feature","line":1,"name":"Counter","uri":"./test_driver/features/counter.feature","elements":[{"keyword":"Scenario","type":"scenario","id":"counter;counter increases when the button is pressed","name":"Counter increases when the button is pressed","description":"","line":4,"steps":[{"keyword":"Given ","name":"I expect the \"counter\" to be \"0\"","line":5,"match":{"location":"./test_driver/features/counter.feature:5"},"result":{"status":"failed","duration":10124000000}},{"keyword":"When ","name":"I tap the \"increment\" button 10 times","line":6,"match":{"location":"./test_driver/features/counter.feature:6"},"result":{"status":"skipped","duration":0}},{"keyword":"Then ","name":"I expect the \"counter\" to be \"10\"","line":7,"match":{"location":"./test_driver/features/counter.feature:7"},"result":{"status":"skipped","duration":0}}]}]}]